chiklisp_puzzles/__init__.py
chiklisp_puzzles/puzzles/calculate_synthetic_public_key.clsp
chiklisp_puzzles/puzzles/calculate_synthetic_public_key.hex
chiklisp_puzzles/puzzles/p2_conditions.clsp
chiklisp_puzzles/puzzles/p2_conditions.hex
chiklisp_puzzles/puzzles/p2_delegated_puzzle_or_hidden_puzzle.clsp
chiklisp_puzzles/puzzles/p2_delegated_puzzle_or_hidden_puzzle.hex
chiklisp_puzzles/puzzles/runtime_build
chiklisp_puzzles-0.1.1.dist-info/LICENSE
chiklisp_puzzles-0.1.1.dist-info/METADATA
chiklisp_puzzles-0.1.1.dist-info/WHEEL
chiklisp_puzzles-0.1.1.dist-info/top_level.txt
chiklisp_puzzles-0.1.1.dist-info/RECORD
