Metadata-Version: 2.1
Name: chiklisp-puzzles
Version: 0.1.1
Summary: Some canonical puzzles deployed on chik-blockchain
Author-email: Richard Kiss <him@richardkiss.com>
License: Copyright 2023 by Richard Kiss
License-File: LICENSE
Requires-Dist: chiklisp-loader >=0.1.2
